{"version": 0.6, "generator": "Overpass API 0.7.62.11 87bfad18", "osm3s": {"timestamp_osm_base": "2026-04-13T12:49:29Z", "copyright": "The data included in this document is from www.openstreetmap.org. The data is made available under ODbL."}, "elements": [{"type": "node", "id": 663330745, "lat": 31.21159, "lon": 96.499083}, {"type": "node", "id": 663330746, "lat": 31.21119, "lon": 96.498588}, {"type": "node", "id": 663330747, "lat": 31.210622, "lon": 96.498075}, {"type": "node", "id": 663330748, "lat": 31.209793, "lon": 96.498048}, {"type": "node", "id": 663330749, "lat": 31.20921, "lon": 96.497998}, {"type": "node", "id": 663330750, "lat": 31.208633, "lon": 96.497978}, {"type": "node", "id": 663330751, "lat": 31.208057, "lon": 96.497942}, {"type": "node", "id": 663330752, "lat": 31.2074691, "lon": 96.4979125}, {"type": "node", "id": 663330753, "lat": 31.216047, "lon": 96.50326}, {"type": "node", "id": 663330754, "lat": 31.2153, "lon": 96.502577}, {"type": "node", "id": 663330755, "lat": 31.214837, "lon": 96.502133}, {"type": "node", "id": 663330756, "lat": 31.214392, "lon": 96.501693}, {"type": "node", "id": 663330757, "lat": 31.213965, "lon": 96.501275}, {"type": "node", "id": 663330758, "lat": 31.21352, "lon": 96.50083}, {"type": "node", "id": 663330759, "lat": 31.213072, "lon": 96.500388}, {"type": "node", "id": 663330760, "lat": 31.212657, "lon": 96.500105}, {"type": "node", "id": 663330761, "lat": 31.212183, "lon": 96.499827}, {"type": "node", "id": 663331090, "lat": 31.22314, "lon": 96.506607}, {"type": "node", "id": 663331091, "lat": 31.222463, "lon": 96.50641}, {"type": "node", "id": 663331093, "lat": 31.221908, "lon": 96.506295}, {"type": "node", "id": 663331094, "lat": 31.22105, "lon": 96.506342}, {"type": "node", "id": 663331095, "lat": 31.220312, "lon": 96.506225}, {"type": "node", "id": 663331096, "lat": 31.219562, "lon": 96.505707}, {"type": "node", "id": 663331097, "lat": 31.219063, "lon": 96.50537}, {"type": "node", "id": 663331098, "lat": 31.21855, "lon": 96.505022}, {"type": "node", "id": 663331099, "lat": 31.217732, "lon": 96.5045}, {"type": "node", "id": 663331101, "lat": 31.216875, "lon": 96.503948}, {"type": "node", "id": 663331102, "lat": 31.228505, "lon": 96.506202}, {"type": "node", "id": 663331104, "lat": 31.227873, "lon": 96.506293}, {"type": "node", "id": 663331106, "lat": 31.227462, "lon": 96.506258}, {"type": "node", "id": 663331108, "lat": 31.226917, "lon": 96.506103}, {"type": "node", "id": 663331109, "lat": 31.226473, "lon": 96.50611}, {"type": "node", "id": 663331110, "lat": 31.226028, "lon": 96.506088}, {"type": "node", "id": 663331111, "lat": 31.22532, "lon": 96.505847}, {"type": "node", "id": 663331112, "lat": 31.224735, "lon": 96.505808}, {"type": "node", "id": 663331113, "lat": 31.223948, "lon": 96.506145}, {"type": "node", "id": 663331114, "lat": 31.223543, "lon": 96.506392}, {"type": "node", "id": 663331115, "lat": 31.234043, "lon": 96.5088256}, {"type": "node", "id": 663331116, "lat": 31.233642, "lon": 96.508243}, {"type": "node", "id": 663331117, "lat": 31.2332593, "lon": 96.5074231}, {"type": "node", "id": 663331118, "lat": 31.232955, "lon": 96.507097}, {"type": "node", "id": 663331119, "lat": 31.23269, "lon": 96.50693}, {"type": "node", "id": 663331120, "lat": 31.231933, "lon": 96.506637}, {"type": "node", "id": 663331121, "lat": 31.23143, "lon": 96.506412}, {"type": "node", "id": 663331122, "lat": 31.231123, "lon": 96.506418}, {"type": "node", "id": 663331123, "lat": 31.2307, "lon": 96.506695}, {"type": "node", "id": 663331124, "lat": 31.229937, "lon": 96.506797}, {"type": "node", "id": 663331125, "lat": 31.229398, "lon": 96.506678}, {"type": "node", "id": 663331126, "lat": 31.228947, "lon": 96.506408}, {"type": "node", "id": 663331127, "lat": 31.239063, "lon": 96.514445}, {"type": "node", "id": 663331129, "lat": 31.23858, "lon": 96.51359}, {"type": "node", "id": 663331130, "lat": 31.238258, "lon": 96.513057}, {"type": "node", "id": 663331131, "lat": 31.237925, "lon": 96.512538}, {"type": "node", "id": 663331132, "lat": 31.23753, "lon": 96.51208}, {"type": "node", "id": 663331133, "lat": 31.23707, "lon": 96.511647}, {"type": "node", "id": 663331134, "lat": 31.236252, "lon": 96.510858}, {"type": "node", "id": 663331135, "lat": 31.235798, "lon": 96.510417}, {"type": "node", "id": 663331136, "lat": 31.235328, "lon": 96.509992}, {"type": "node", "id": 663331137, "lat": 31.234485, "lon": 96.509302}, {"type": "node", "id": 663331141, "lat": 31.2414763, "lon": 96.5182375}, {"type": "node", "id": 663331143, "lat": 31.2409787, "lon": 96.5166615}, {"type": "node", "id": 663331145, "lat": 31.2408164, "lon": 96.5164253}, {"type": "node", "id": 663331146, "lat": 31.2405428, "lon": 96.516116}, {"type": "node", "id": 663331147, "lat": 31.239753, "lon": 96.515208}, {"type": "node", "id": 663331287, "lat": 31.2082215, "lon": 96.6005436}, {"type": "node", "id": 663331289, "lat": 31.208581, "lon": 96.6002904}, {"type": "node", "id": 663331294, "lat": 31.210922, "lon": 96.600108}, {"type": "node", "id": 663331309, "lat": 31.215818, "lon": 96.600432}, {"type": "node", "id": 663331310, "lat": 31.217442, "lon": 96.600647}, {"type": "node", "id": 663331311, "lat": 31.217777, "lon": 96.60076}, {"type": "node", "id": 663331320, "lat": 31.2210989, "lon": 96.6020836}, {"type": "node", "id": 663331322, "lat": 31.22126, "lon": 96.602148}, {"type": "node", "id": 663331324, "lat": 31.221977, "lon": 96.602437}, {"type": "node", "id": 663331327, "lat": 31.22303, "lon": 96.602777}, {"type": "node", "id": 663331347, "lat": 31.224122, "lon": 96.603232}, {"type": "node", "id": 663331348, "lat": 31.224548, "lon": 96.60335}, {"type": "node", "id": 663331350, "lat": 31.225487, "lon": 96.603408}, {"type": "node", "id": 663331351, "lat": 31.2256776, "lon": 96.6033811}, {"type": "node", "id": 663331352, "lat": 31.2258187, "lon": 96.6032881}, {"type": "node", "id": 1936905289, "lat": 31.2529839, "lon": 96.5949296}, {"type": "node", "id": 2034743092, "lat": 31.2238274, "lon": 96.5984795}, {"type": "node", "id": 2034743094, "lat": 31.2169888, "lon": 96.600587}, {"type": "node", "id": 2034743097, "lat": 31.2151498, "lon": 96.6037054}, {"type": "node", "id": 2034743099, "lat": 31.2220194, "lon": 96.5998654}, {"type": "node", "id": 2034743100, "lat": 31.2215085, "lon": 96.6090213}, {"type": "node", "id": 2034743103, "lat": 31.2277402, "lon": 96.6099657}, {"type": "node", "id": 2034743107, "lat": 31.2203391, "lon": 96.6072139}, {"type": "node", "id": 2034743108, "lat": 31.2288367, "lon": 96.6092292}, {"type": "node", "id": 2034743109, "lat": 31.213539, "lon": 96.600292}, {"type": "node", "id": 2034743110, "lat": 31.214139, "lon": 96.6021333}, {"type": "node", "id": 2034743111, "lat": 31.2134166, "lon": 96.6020831}, {"type": "node", "id": 2034743112, "lat": 31.2215019, "lon": 96.6056034}, {"type": "node", "id": 2034743113, "lat": 31.2238322, "lon": 96.5976907}, {"type": "node", "id": 2034743114, "lat": 31.2175198, "lon": 96.6015639}, {"type": "node", "id": 2034743115, "lat": 31.2226151, "lon": 96.6051927}, {"type": "node", "id": 2034743116, "lat": 31.2159685, "lon": 96.607448}, {"type": "node", "id": 2034743117, "lat": 31.2133542, "lon": 96.6031153}, {"type": "node", "id": 2034743118, "lat": 31.2249746, "lon": 96.603835}, {"type": "node", "id": 2034743120, "lat": 31.2153401, "lon": 96.607453}, {"type": "node", "id": 2034743121, "lat": 31.227986, "lon": 96.6097029}, {"type": "node", "id": 2034743124, "lat": 31.2151434, "lon": 96.6075185}, {"type": "node", "id": 2034743127, "lat": 31.2237313, "lon": 96.5974226}, {"type": "node", "id": 2034743130, "lat": 31.2223751, "lon": 96.6092391}, {"type": "node", "id": 2034743133, "lat": 31.2287743, "lon": 96.6093635}, {"type": "node", "id": 2034743134, "lat": 31.2217082, "lon": 96.6056057}, {"type": "node", "id": 2034743135, "lat": 31.2209789, "lon": 96.5980342}, {"type": "node", "id": 2034743137, "lat": 31.2214962, "lon": 96.597791}, {"type": "node", "id": 2034743138, "lat": 31.214045, "lon": 96.6033441}, {"type": "node", "id": 2034743140, "lat": 31.2219239, "lon": 96.5999332}, {"type": "node", "id": 2034743142, "lat": 31.2171981, "lon": 96.6043328}, {"type": "node", "id": 2034743143, "lat": 31.2164888, "lon": 96.6041083}, {"type": "node", "id": 2034743144, "lat": 31.2166182, "lon": 96.6005379}, {"type": "node", "id": 2034743145, "lat": 31.2274727, "lon": 96.6098702}, {"type": "node", "id": 2034743152, "lat": 31.223135, "lon": 96.6020575}, {"type": "node", "id": 2034743154, "lat": 31.2215375, "lon": 96.6000608}, {"type": "node", "id": 2034743155, "lat": 31.225197, "lon": 96.6097458}, {"type": "node", "id": 2034743156, "lat": 31.2221005, "lon": 96.5960644}, {"type": "node", "id": 2034743157, "lat": 31.2207128, "lon": 96.6004052}, {"type": "node", "id": 2034743159, "lat": 31.2150525, "lon": 96.6075227}, {"type": "node", "id": 2034743160, "lat": 31.2141988, "lon": 96.6003304}, {"type": "node", "id": 2034743162, "lat": 31.2159233, "lon": 96.607497}, {"type": "node", "id": 2034743163, "lat": 31.2240919, "lon": 96.5981659}, {"type": "node", "id": 2034743165, "lat": 31.219913, "lon": 96.6052169}, {"type": "node", "id": 2034743166, "lat": 31.2178798, "lon": 96.6070499}, {"type": "node", "id": 2034743167, "lat": 31.2194595, "lon": 96.5996117}, {"type": "node", "id": 2034743169, "lat": 31.2291604, "lon": 96.6091986}, {"type": "node", "id": 2034743170, "lat": 31.2205201, "lon": 96.6008943}, {"type": "node", "id": 2034743174, "lat": 31.2211853, "lon": 96.5978062}, {"type": "node", "id": 2034743175, "lat": 31.2235639, "lon": 96.5973223}, {"type": "node", "id": 2034743176, "lat": 31.2214972, "lon": 96.5960976}, {"type": "node", "id": 2034743178, "lat": 31.2207679, "lon": 96.6011563}, {"type": "node", "id": 2034743179, "lat": 31.2189145, "lon": 96.6067889}, {"type": "node", "id": 2034743180, "lat": 31.2213894, "lon": 96.5978115}, {"type": "node", "id": 2034743182, "lat": 31.2172996, "lon": 96.6023204}, {"type": "node", "id": 2034743185, "lat": 31.2189879, "lon": 96.6032377}, {"type": "node", "id": 2034743187, "lat": 31.2165371, "lon": 96.6022916}, {"type": "node", "id": 2034743190, "lat": 31.2118658, "lon": 96.6025049}, {"type": "node", "id": 2034743191, "lat": 31.2247334, "lon": 96.6095843}, {"type": "node", "id": 2034743193, "lat": 31.2237038, "lon": 96.6022292}, {"type": "node", "id": 2034743196, "lat": 31.2253986, "lon": 96.6097069}, {"type": "node", "id": 3039555034, "lat": 31.2160652, "lon": 96.6074036}, {"type": "node", "id": 3039555035, "lat": 31.2204963, "lon": 96.6080747}, {"type": "node", "id": 3039555036, "lat": 31.2163706, "lon": 96.6076914}, {"type": "node", "id": 3039555037, "lat": 31.2211096, "lon": 96.6085551}, {"type": "node", "id": 3039555038, "lat": 31.2171091, "lon": 96.6072579}, {"type": "node", "id": 3039555039, "lat": 31.2198402, "lon": 96.6076778}, {"type": "node", "id": 3039555040, "lat": 31.2301099, "lon": 96.6084264}, {"type": "node", "id": 3039555041, "lat": 31.221664, "lon": 96.6090937}, {"type": "node", "id": 3039555042, "lat": 31.2146057, "lon": 96.6073505}, {"type": "node", "id": 3039555043, "lat": 31.2316098, "lon": 96.6071282}, {"type": "node", "id": 3039555044, "lat": 31.2276062, "lon": 96.6099534}, {"type": "node", "id": 3039555045, "lat": 31.2205551, "lon": 96.6073645}, {"type": "node", "id": 3039555046, "lat": 31.2294172, "lon": 96.6092632}, {"type": "node", "id": 3039555047, "lat": 31.2148488, "lon": 96.6074686}, {"type": "node", "id": 3039555049, "lat": 31.2156551, "lon": 96.6075282}, {"type": "node", "id": 3039555050, "lat": 31.2305057, "lon": 96.6083644}, {"type": "node", "id": 3039555051, "lat": 31.2155861, "lon": 96.6076593}, {"type": "node", "id": 3039555052, "lat": 31.218215, "lon": 96.6069113}, {"type": "node", "id": 3039555053, "lat": 31.2160875, "lon": 96.6076509}, {"type": "node", "id": 3039555054, "lat": 31.2289266, "lon": 96.6091814}, {"type": "node", "id": 3039555055, "lat": 31.2183676, "lon": 96.6074686}, {"type": "node", "id": 3039555056, "lat": 31.2154177, "lon": 96.6076295}, {"type": "node", "id": 3039555057, "lat": 31.2311511, "lon": 96.6076163}, {"type": "node", "id": 3039555058, "lat": 31.2152125, "lon": 96.6074815}, {"type": "node", "id": 3039555059, "lat": 31.2221533, "lon": 96.6092506}, {"type": "node", "id": 3039555060, "lat": 31.2262298, "lon": 96.6097415}, {"type": "node", "id": 3039555061, "lat": 31.2210244, "lon": 96.6077193}, {"type": "node", "id": 3039555062, "lat": 31.2196416, "lon": 96.6076914}, {"type": "node", "id": 3039555063, "lat": 31.225061, "lon": 96.6097503}, {"type": "node", "id": 3039555064, "lat": 31.2294828, "lon": 96.6090511}, {"type": "node", "id": 3039555065, "lat": 31.2212893, "lon": 96.6078083}, {"type": "node", "id": 3039555066, "lat": 31.2194044, "lon": 96.6076295}, {"type": "node", "id": 3039555067, "lat": 31.220716, "lon": 96.6075036}, {"type": "node", "id": 3039555068, "lat": 31.2235965, "lon": 96.6094456}, {"type": "node", "id": 3039555069, "lat": 31.2202701, "lon": 96.607965}, {"type": "node", "id": 3039555070, "lat": 31.2279269, "lon": 96.6097423}, {"type": "node", "id": 3039555071, "lat": 31.2238295, "lon": 96.6094915}, {"type": "node", "id": 3039555072, "lat": 31.2165163, "lon": 96.6073639}, {"type": "node", "id": 3039555073, "lat": 31.2295044, "lon": 96.6089521}, {"type": "node", "id": 3039555074, "lat": 31.2293484, "lon": 96.6092525}, {"type": "node", "id": 3039555075, "lat": 31.2188401, "lon": 96.60749}, {"type": "node", "id": 3039555077, "lat": 31.2278165, "lon": 96.6099292}, {"type": "node", "id": 3039555078, "lat": 31.2322245, "lon": 96.6070906}, {"type": "node", "id": 3039555079, "lat": 31.2265149, "lon": 96.6097559}, {"type": "node", "id": 3039555080, "lat": 31.2199535, "lon": 96.6076861}, {"type": "node", "id": 3039555081, "lat": 31.2286757, "lon": 96.6094716}, {"type": "node", "id": 3039555082, "lat": 31.230853, "lon": 96.608185}, {"type": "node", "id": 3039555083, "lat": 31.224941, "lon": 96.6096983}, {"type": "node", "id": 3039555084, "lat": 31.2158031, "lon": 96.607667}, {"type": "node", "id": 3039555085, "lat": 31.2266485, "lon": 96.6097753}, {"type": "node", "id": 3039555086, "lat": 31.2200375, "lon": 96.6077314}, {"type": "node", "id": 3039555087, "lat": 31.2258261, "lon": 96.609739}, {"type": "node", "id": 3039555088, "lat": 31.2299264, "lon": 96.6085229}, {"type": "node", "id": 3039555089, "lat": 31.2141593, "lon": 96.6073267}, {"type": "node", "id": 3039555090, "lat": 31.2284058, "lon": 96.609507}, {"type": "node", "id": 3039555091, "lat": 31.2201325, "lon": 96.6078363}, {"type": "node", "id": 3039555093, "lat": 31.227217, "lon": 96.6097482}, {"type": "node", "id": 3039555094, "lat": 31.216973, "lon": 96.6077046}, {"type": "node", "id": 3039555095, "lat": 31.2270133, "lon": 96.609772}, {"type": "node", "id": 3039555096, "lat": 31.2154129, "lon": 96.6074628}, {"type": "node", "id": 3039555098, "lat": 31.2309644, "lon": 96.6080586}, {"type": "node", "id": 3039555100, "lat": 31.2312337, "lon": 96.6073589}, {"type": "node", "id": 3039555101, "lat": 31.2137065, "lon": 96.6072593}, {"type": "node", "id": 3039555102, "lat": 31.2317704, "lon": 96.6071282}, {"type": "node", "id": 3039555103, "lat": 31.2213518, "lon": 96.607739}, {"type": "node", "id": 3039555104, "lat": 31.2186315, "lon": 96.6067849}, {"type": "node", "id": 3039555105, "lat": 31.2181428, "lon": 96.607431}, {"type": "node", "id": 3039555106, "lat": 31.2191755, "lon": 96.6068347}, {"type": "node", "id": 3039555107, "lat": 31.2179777, "lon": 96.6074578}, {"type": "node", "id": 3039555108, "lat": 31.2313438, "lon": 96.6071604}, {"type": "node", "id": 3039555109, "lat": 31.2159545, "lon": 96.6076509}, {"type": "node", "id": 3039555110, "lat": 31.2208206, "lon": 96.6083298}, {"type": "node", "id": 3039555111, "lat": 31.2158308, "lon": 96.6075296}, {"type": "node", "id": 3039555112, "lat": 31.2303177, "lon": 96.608402}, {"type": "node", "id": 3039555113, "lat": 31.2194295, "lon": 96.6068645}, {"type": "node", "id": 3039555114, "lat": 31.2325515, "lon": 96.6070018}, {"type": "node", "id": 3039555115, "lat": 31.2143855, "lon": 96.607313}, {"type": "node", "id": 3039555116, "lat": 31.2199321, "lon": 96.6070787}, {"type": "node", "id": 3039555117, "lat": 31.2211628, "lon": 96.607801}, {"type": "node", "id": 3039555118, "lat": 31.21404, "lon": 96.6073052}, {"type": "node", "id": 3039555119, "lat": 31.2171748, "lon": 96.6076885}, {"type": "node", "id": 3039555121, "lat": 31.215326, "lon": 96.6075973}, {"type": "node", "id": 3039555122, "lat": 31.2282275, "lon": 96.6096189}, {"type": "node", "id": 3039555123, "lat": 31.2245504, "lon": 96.6095368}, {"type": "node", "id": 3039555124, "lat": 31.2295044, "lon": 96.6091559}, {"type": "node", "id": 3039555125, "lat": 31.229486, "lon": 96.6092364}, {"type": "node", "id": 3039555126, "lat": 31.2162206, "lon": 96.6076724}, {"type": "node", "id": 3039555127, "lat": 31.226822, "lon": 96.6097138}, {"type": "node", "id": 3039555128, "lat": 31.2185727, "lon": 96.607493}, {"type": "node", "id": 3039555129, "lat": 31.2287998, "lon": 96.6092962}, {"type": "node", "id": 3039555130, "lat": 31.2174166, "lon": 96.6076271}, {"type": "node", "id": 3039555131, "lat": 31.2184018, "lon": 96.6068381}, {"type": "node", "id": 3039555132, "lat": 31.2166014, "lon": 96.6076831}, {"type": "node", "id": 3039555233, "lat": 31.2314447, "lon": 96.6071067}, {"type": "node", "id": 3039555235, "lat": 31.229697, "lon": 96.608759}, {"type": "node", "id": 3134774902, "lat": 31.2121409, "lon": 96.6001911}, {"type": "node", "id": 3134774904, "lat": 31.2147468, "lon": 96.6035581}, {"type": "node", "id": 3134774905, "lat": 31.2148234, "lon": 96.6021829}, {"type": "node", "id": 3134774906, "lat": 31.2148841, "lon": 96.6003734}, {"type": "node", "id": 3134774907, "lat": 31.2159107, "lon": 96.5994028}, {"type": "node", "id": 3694599384, "lat": 31.200642, "lon": 96.6094358}, {"type": "node", "id": 3694599385, "lat": 31.2010426, "lon": 96.6092986}, {"type": "node", "id": 3694599386, "lat": 31.2027417, "lon": 96.6085718}, {"type": "node", "id": 3694599387, "lat": 31.2043165, "lon": 96.6079339}, {"type": "node", "id": 3694599388, "lat": 31.2047033, "lon": 96.6076593}, {"type": "node", "id": 3694599389, "lat": 31.2051384, "lon": 96.6075543}, {"type": "node", "id": 3694599390, "lat": 31.20645, "lon": 96.607174}, {"type": "node", "id": 3694599391, "lat": 31.2067138, "lon": 96.6070484}, {"type": "node", "id": 3694599392, "lat": 31.2069628, "lon": 96.6072082}, {"type": "node", "id": 3694599393, "lat": 31.2072625, "lon": 96.6075107}, {"type": "node", "id": 3694599394, "lat": 31.2076575, "lon": 96.6074841}, {"type": "node", "id": 3694599395, "lat": 31.2083132, "lon": 96.6070827}, {"type": "node", "id": 3694599396, "lat": 31.2086679, "lon": 96.6067235}, {"type": "node", "id": 3694599397, "lat": 31.2088773, "lon": 96.6066258}, {"type": "node", "id": 3694599398, "lat": 31.2090666, "lon": 96.6010044}, {"type": "node", "id": 3694599400, "lat": 31.2091061, "lon": 96.6001093}, {"type": "node", "id": 3694599401, "lat": 31.209982, "lon": 96.6070188}, {"type": "node", "id": 3694599403, "lat": 31.2104303, "lon": 96.607094}, {"type": "node", "id": 3694599404, "lat": 31.2109772, "lon": 96.6069684}, {"type": "node", "id": 3694599405, "lat": 31.2115574, "lon": 96.6023293}, {"type": "node", "id": 3694599407, "lat": 31.2116707, "lon": 96.6068656}, {"type": "node", "id": 3694599408, "lat": 31.2123153, "lon": 96.6070141}, {"type": "node", "id": 3694599409, "lat": 31.2129404, "lon": 96.6071854}, {"type": "node", "id": 3694601972, "lat": 31.233572, "lon": 96.6068267}, {"type": "node", "id": 3694601976, "lat": 31.2341106, "lon": 96.6068751}, {"type": "node", "id": 3694601987, "lat": 31.2356572, "lon": 96.6068913}, {"type": "node", "id": 3694601991, "lat": 31.2361267, "lon": 96.6070205}, {"type": "node", "id": 3694601998, "lat": 31.237121, "lon": 96.6082318}, {"type": "node", "id": 3694602000, "lat": 31.2373005, "lon": 96.6073597}, {"type": "node", "id": 3694602001, "lat": 31.2373143, "lon": 96.6081833}, {"type": "node", "id": 3694602002, "lat": 31.2373557, "lon": 96.6069882}, {"type": "node", "id": 3694602005, "lat": 31.2377148, "lon": 96.6067136}, {"type": "node", "id": 3694602008, "lat": 31.2385985, "lon": 96.606536}, {"type": "node", "id": 3694602014, "lat": 31.2392475, "lon": 96.6069559}, {"type": "node", "id": 3694602021, "lat": 31.2394961, "lon": 96.6071982}, {"type": "node", "id": 3694602022, "lat": 31.2395651, "lon": 96.6065037}, {"type": "node", "id": 3694602024, "lat": 31.2396756, "lon": 96.6070367}, {"type": "node", "id": 3694602025, "lat": 31.2396894, "lon": 96.6060515}, {"type": "node", "id": 3694602033, "lat": 31.2405732, "lon": 96.6056316}, {"type": "node", "id": 3694602038, "lat": 31.2415812, "lon": 96.6057285}, {"type": "node", "id": 3694602040, "lat": 31.2420092, "lon": 96.6055024}, {"type": "node", "id": 3694602047, "lat": 31.2425754, "lon": 96.6051955}, {"type": "node", "id": 3694602057, "lat": 31.2437077, "lon": 96.6050663}, {"type": "node", "id": 3694602060, "lat": 31.2440252, "lon": 96.605244}, {"type": "node", "id": 3694602066, "lat": 31.244329, "lon": 96.6051794}, {"type": "node", "id": 3694602083, "lat": 31.2455579, "lon": 96.603419}, {"type": "node", "id": 3694602088, "lat": 31.245765, "lon": 96.6031121}, {"type": "node", "id": 3694602106, "lat": 31.2479052, "lon": 96.5987838}, {"type": "node", "id": 3694602107, "lat": 31.2479328, "lon": 96.6012225}, {"type": "node", "id": 3694602109, "lat": 31.2479466, "lon": 96.5979924}, {"type": "node", "id": 3694602110, "lat": 31.2481814, "lon": 96.6007057}, {"type": "node", "id": 3694602111, "lat": 31.2481952, "lon": 96.5998013}, {"type": "node", "id": 3694602112, "lat": 31.248278, "lon": 96.5969588}, {"type": "node", "id": 3694602115, "lat": 31.2484989, "lon": 96.5963935}, {"type": "node", "id": 3694602119, "lat": 31.2494516, "lon": 96.5953276}, {"type": "node", "id": 3694602121, "lat": 31.2497416, "lon": 96.5952469}, {"type": "node", "id": 3694602124, "lat": 31.2501972, "lon": 96.5954407}, {"type": "node", "id": 3694602229, "lat": 31.2513018, "lon": 96.5952953}, {"type": "node", "id": 3694602233, "lat": 31.2518541, "lon": 96.5952792}, {"type": "node", "id": 3694602236, "lat": 31.2522683, "lon": 96.5950369}, {"type": "node", "id": 4089433776, "lat": 31.216938, "lon": 96.5986842}, {"type": "node", "id": 4089433777, "lat": 31.2174096, "lon": 96.5987415}, {"type": "node", "id": 4089433778, "lat": 31.2175443, "lon": 96.5988346}, {"type": "node", "id": 4089433779, "lat": 31.2175994, "lon": 96.5990495}, {"type": "node", "id": 4089433780, "lat": 31.2176791, "lon": 96.5991354}, {"type": "node", "id": 4089433781, "lat": 31.2178643, "lon": 96.5991654}, {"type": "node", "id": 4089433782, "lat": 31.2182976, "lon": 96.5992356}, {"type": "node", "id": 4089433783, "lat": 31.2190999, "lon": 96.5993001}, {"type": "node", "id": 4089727258, "lat": 31.2129493, "lon": 96.5980594}, {"type": "node", "id": 4089727260, "lat": 31.2132908, "lon": 96.5980844}, {"type": "node", "id": 4089727261, "lat": 31.2137178, "lon": 96.5981592}, {"type": "node", "id": 4089727262, "lat": 31.2141163, "lon": 96.5981925}, {"type": "node", "id": 4089727263, "lat": 31.2151124, "lon": 96.5984088}, {"type": "node", "id": 4089727264, "lat": 31.2155038, "lon": 96.5985669}, {"type": "node", "id": 4089727265, "lat": 31.2161727, "lon": 96.5988581}, {"type": "node", "id": 4089727266, "lat": 31.2165996, "lon": 96.5991576}, {"type": "node", "id": 4089727267, "lat": 31.217055, "lon": 96.5995071}, {"type": "node", "id": 4089727268, "lat": 31.2172756, "lon": 96.5996901}, {"type": "node", "id": 4089727269, "lat": 31.2174534, "lon": 96.5997567}, {"type": "node", "id": 4089727270, "lat": 31.2178292, "lon": 96.5998076}, {"type": "node", "id": 4089727273, "lat": 31.2225665, "lon": 96.599477}, {"type": "node", "id": 4089727283, "lat": 31.2241694, "lon": 96.598044}, {"type": "node", "id": 6875508684, "lat": 31.2088227, "lon": 96.6001665}, {"type": "node", "id": 6875510160, "lat": 31.2411039, "lon": 96.5169291}, {"type": "node", "id": 6875520999, "lat": 31.2193758, "lon": 96.6041935}, {"type": "node", "id": 6875556586, "lat": 31.2545445, "lon": 96.4922574}, {"type": "node", "id": 6875556595, "lat": 31.2544436, "lon": 96.4919999}, {"type": "node", "id": 6875556608, "lat": 31.2545192, "lon": 96.4921394}, {"type": "node", "id": 6875556610, "lat": 31.2543255, "lon": 96.4918685}, {"type": "node", "id": 6875556615, "lat": 31.2544124, "lon": 96.4928501}, {"type": "node", "id": 6875556617, "lat": 31.2545284, "lon": 96.4925136}, {"type": "node", "id": 6875556619, "lat": 31.2545491, "lon": 96.4923822}, {"type": "node", "id": 9267280133, "lat": 31.2063637, "lon": 96.4977028}, {"type": "node", "id": 9267280134, "lat": 31.2068794, "lon": 96.4978149}, {"type": "node", "id": 9267280138, "lat": 31.2077781, "lon": 96.497928}, {"type": "node", "id": 12557378636, "lat": 31.2000829, "lon": 96.6096442}, {"type": "node", "id": 13063762681, "lat": 31.2399626, "lon": 96.4840525}, {"type": "node", "id": 13063762682, "lat": 31.240701, "lon": 96.4846963}, {"type": "node", "id": 13063762683, "lat": 31.2412789, "lon": 96.4851361}, {"type": "node", "id": 13063762684, "lat": 31.2432924, "lon": 96.4863753}, {"type": "node", "id": 13063762685, "lat": 31.2435905, "lon": 96.4866972}, {"type": "node", "id": 13063762689, "lat": 31.2123587, "lon": 96.4999554}, {"type": "node", "id": 13063795034, "lat": 31.2515463, "lon": 96.4925089}, {"type": "node", "id": 13063795043, "lat": 31.2540143, "lon": 96.4916631}, {"type": "node", "id": 13063795044, "lat": 31.2539185, "lon": 96.4916539}, {"type": "node", "id": 13063795045, "lat": 31.2538268, "lon": 96.4916646}, {"type": "node", "id": 13063795046, "lat": 31.2534829, "lon": 96.4917773}, {"type": "node", "id": 13063795047, "lat": 31.2527445, "lon": 96.4920589}, {"type": "node", "id": 13063795048, "lat": 31.2519489, "lon": 96.4923862}, {"type": "node", "id": 13063795049, "lat": 31.2511922, "lon": 96.4926168}, {"type": "node", "id": 13063795050, "lat": 31.2508047, "lon": 96.4927456}, {"type": "node", "id": 13063795051, "lat": 31.2505639, "lon": 96.4928019}, {"type": "node", "id": 13063795052, "lat": 31.2504263, "lon": 96.4928073}, {"type": "node", "id": 13063795053, "lat": 31.2500502, "lon": 96.4926034}, {"type": "node", "id": 13063795054, "lat": 31.2493577, "lon": 96.4920777}, {"type": "node", "id": 13063795055, "lat": 31.2492202, "lon": 96.4919087}, {"type": "node", "id": 13063795056, "lat": 31.2485827, "lon": 96.4914393}, {"type": "node", "id": 13063795057, "lat": 31.2483694, "lon": 96.4912114}, {"type": "node", "id": 13063795058, "lat": 31.2481057, "lon": 96.4908814}, {"type": "node", "id": 13063795059, "lat": 31.2474843, "lon": 96.4899829}, {"type": "node", "id": 13063795060, "lat": 31.2474109, "lon": 96.4898863}, {"type": "node", "id": 13063795061, "lat": 31.2471174, "lon": 96.489661}, {"type": "node", "id": 13063795062, "lat": 31.2468445, "lon": 96.4893606}, {"type": "node", "id": 13063795063, "lat": 31.2466221, "lon": 96.4890656}, {"type": "node", "id": 13063795064, "lat": 31.2463102, "lon": 96.4888054}, {"type": "node", "id": 13063795065, "lat": 31.2458722, "lon": 96.4883924}, {"type": "node", "id": 13063795066, "lat": 31.2456933, "lon": 96.4882743}, {"type": "node", "id": 13063795067, "lat": 31.2450329, "lon": 96.4880088}, {"type": "node", "id": 13063795068, "lat": 31.2448288, "lon": 96.4878613}, {"type": "node", "id": 13063795069, "lat": 31.2441225, "lon": 96.4872739}, {"type": "node", "id": 13063795226, "lat": 31.2206779, "lon": 96.5063532}, {"type": "node", "id": 13065386869, "lat": 31.2186348, "lon": 96.6001278}, {"type": "node", "id": 13065386870, "lat": 31.2184447, "lon": 96.601026}, {"type": "node", "id": 13065398235, "lat": 31.2228393, "lon": 96.5967643}, {"type": "node", "id": 13065398236, "lat": 31.2246651, "lon": 96.5979445}, {"type": "node", "id": 13065398239, "lat": 31.2204808, "lon": 96.6010306}, {"type": "node", "id": 13065398240, "lat": 31.2202723, "lon": 96.6017542}, {"type": "node", "id": 13065398241, "lat": 31.220518, "lon": 96.6007125}, {"type": "node", "id": 13065398242, "lat": 31.2206144, "lon": 96.6005033}, {"type": "node", "id": 13065418965, "lat": 31.2098032, "lon": 96.6068897}, {"type": "node", "id": 13065418966, "lat": 31.2092022, "lon": 96.6066831}, {"type": "node", "id": 13065418967, "lat": 31.2071169, "lon": 96.607469}, {"type": "node", "id": 13065418968, "lat": 31.2070366, "lon": 96.6073912}, {"type": "node", "id": 13065418999, "lat": 31.2157629, "lon": 96.602971}, {"type": "node", "id": 13065419000, "lat": 31.2158063, "lon": 96.602246}, {"type": "node", "id": 13065419026, "lat": 31.2211098, "lon": 96.5978694}, {"type": "node", "id": 13065419029, "lat": 31.2225836, "lon": 96.596522}, {"type": "node", "id": 13065419030, "lat": 31.2214126, "lon": 96.5955949}, {"type": "node", "id": 13065419031, "lat": 31.2221663, "lon": 96.5960289}, {"type": "node", "id": 13065419032, "lat": 31.222025, "lon": 96.5956432}, {"type": "node", "id": 13065419033, "lat": 31.2216534, "lon": 96.595619}, {"type": "node", "id": 13065419034, "lat": 31.2217131, "lon": 96.5957236}, {"type": "node", "id": 13065419035, "lat": 31.2218163, "lon": 96.5958336}, {"type": "node", "id": 13116854093, "lat": 31.221077, "lon": 96.6055}, {"type": "node", "id": 13116854097, "lat": 31.2220619, "lon": 96.6024644}, {"type": "way", "id": 192941653, "nodes": [2034743143, 2034743187, 2034743144], "tags": {"highway": "residential", "name": "\u5bcc\u6c11\u8def"}}, {"type": "way", "id": 192941655, "nodes": [4089433776, 4089433777, 4089433778, 4089433779, 4089433780, 4089433781, 4089433782, 4089433783, 2034743167, 2034743170], "tags": {"highway": "residential"}}, {"type": "way", "id": 192941656, "nodes": [13065419030, 2034743176, 2034743137], "tags": {"highway": "residential"}}, {"type": "way", "id": 192941659, "nodes": [13065398236, 4089727283, 2034743163, 2034743092, 4089727273, 2034743099, 2034743140, 2034743154, 2034743157, 13065398242, 13065398241, 2034743170, 13065398239, 13065398240], "tags": {"highway": "residential"}}, {"type": "way", "id": 192941660, "nodes": [13065419033, 13065419034, 13065419035, 2034743156, 13065419029, 13065398235, 2034743175, 2034743127, 2034743113], "tags": {"highway": "residential"}}, {"type": "way", "id": 192941661, "nodes": [2034743182, 2034743187, 13065419000, 3134774905, 2034743110, 2034743111], "tags": {"highway": "residential", "name": "\u53d1\u5c55\u8def"}}, {"type": "way", "id": 192941662, "nodes": [2034743142, 2034743182, 2034743114], "tags": {"highway": "residential"}}, {"type": "way", "id": 192941663, "nodes": [663331351, 2034743118, 2034743115, 2034743134, 2034743112, 13116854093, 2034743165, 2034743142, 2034743143, 2034743097, 3134774904, 2034743138, 2034743117, 2034743190, 3694599405, 3694599398, 663331287], "tags": {"highway": "tertiary", "name": "\u6ee8\u6c5f\u8def"}}, {"type": "way", "id": 192941664, "nodes": [2034743180, 2034743174, 13065419026, 2034743135], "tags": {"highway": "residential"}}, {"type": "way", "id": 192941665, "nodes": [2034743165, 6875520999, 2034743185, 2034743114, 2034743094], "tags": {"highway": "residential"}}, {"type": "way", "id": 192941666, "nodes": [12557378636, 3694599384, 3694599385, 3694599386, 3694599387, 3694599388, 3694599389, 3694599390, 3694599391, 3694599392, 13065418968, 13065418967, 3694599393, 3694599394, 3694599395, 3694599396, 3694599397, 13065418966, 13065418965, 3694599401, 3694599403, 3694599404, 3694599407, 3694599408, 3694599409, 3039555101, 3039555118, 3039555089, 3039555115, 3039555042, 3039555047, 2034743159, 2034743124, 3039555058, 2034743120, 3039555096, 3039555049, 3039555111, 2034743162, 2034743116, 3039555034, 3039555072, 3039555038, 2034743166, 3039555052, 3039555131, 3039555104, 2034743179, 3039555106, 3039555113, 3039555116, 2034743107, 3039555045, 3039555067, 3039555061, 3039555117, 3039555065, 3039555103], "tags": {"highway": "unclassified"}}, {"type": "way", "id": 192941670, "nodes": [3039555058, 3039555121, 3039555056, 3039555051, 3039555084, 3039555109, 3039555053, 3039555126, 3039555036, 3039555132, 3039555094, 3039555119, 3039555130, 3039555107, 3039555105, 3039555055, 3039555128, 3039555075, 3039555066, 3039555062, 3039555039, 3039555080, 3039555086, 3039555091, 3039555069, 3039555035, 3039555110, 3039555037, 2034743100, 3039555041, 3039555059, 2034743130, 3039555068, 3039555071, 3039555123, 2034743191, 3039555083, 3039555063, 2034743155, 2034743196, 3039555087, 3039555060, 3039555079, 3039555085, 3039555127, 3039555095, 3039555093, 2034743145, 3039555044, 2034743103, 3039555077, 3039555070, 2034743121, 3039555122, 3039555090, 3039555081, 2034743133, 3039555129, 2034743108, 3039555054, 2034743169, 3039555074, 3039555046, 3039555125, 3039555124, 3039555064, 3039555073, 3039555235, 3039555088, 3039555040, 3039555112, 3039555050, 3039555082, 3039555098, 3039555057, 3039555100, 3039555108, 3039555233, 3039555043, 3039555102, 3039555078, 3039555114, 3694601972, 3694601976, 3694601987, 3694601991, 3694601998, 3694602001, 3694602000, 3694602002, 3694602005, 3694602008, 3694602014, 3694602021, 3694602024, 3694602022, 3694602025, 3694602033, 3694602038, 3694602040, 3694602047, 3694602057, 3694602060, 3694602066, 3694602083, 3694602088, 3694602107, 3694602110, 3694602111, 3694602106, 3694602109, 3694602112, 3694602115, 3694602119, 3694602121, 3694602124, 3694602229, 3694602233, 3694602236, 1936905289], "tags": {"highway": "unclassified"}}, {"type": "way", "id": 192941671, "nodes": [2034743138, 2034743110, 2034743160], "tags": {"highway": "residential", "name": "\u5e73\u5b89\u8def"}}, {"type": "way", "id": 192941672, "nodes": [2034743109, 2034743111, 2034743117], "tags": {"highway": "residential", "name": "\u5c0f\u5eb7\u8def"}}, {"type": "way", "id": 308187224, "nodes": [3134774907, 663331309], "tags": {"highway": "residential", "name": "\u548c\u8c10\u8def"}}, {"type": "way", "id": 308187225, "nodes": [3134774906, 3134774905, 3134774904], "tags": {"highway": "residential", "name": "\u56e2\u7ed3\u8def"}}, {"type": "way", "id": 406899178, "nodes": [4089433781, 4089727270, 663331311], "tags": {"highway": "residential", "source": "bing"}}, {"type": "way", "id": 406936921, "nodes": [4089727258, 4089727260, 4089727261, 4089727262, 4089727263, 4089727264, 4089727265, 4089727266, 4089727267, 4089727268, 4089727269, 4089727270], "tags": {"highway": "residential", "source": "bing"}}, {"type": "way", "id": 734176633, "nodes": [663331287, 663331289, 6875508684, 3694599400, 663331294, 3134774902, 2034743109, 2034743160, 3134774906, 663331309, 2034743144, 2034743094, 663331310, 663331311, 13065386870, 13065398240, 663331320, 663331322, 663331324, 13116854097, 663331327, 663331347, 663331348, 663331350, 663331351, 663331352], "tags": {"highway": "trunk", "ref": "G214;G317", "source": "GPS"}}, {"type": "way", "id": 734179688, "nodes": [6875556615, 6875556617, 6875556619, 6875556586, 6875556608, 6875556595, 6875556610, 13063795043, 13063795044, 13063795045, 13063795046, 13063795047, 13063795048, 13063795034, 13063795049, 13063795050, 13063795051, 13063795052, 13063795053, 13063795054, 13063795055, 13063795056, 13063795057, 13063795058, 13063795059, 13063795060, 13063795061, 13063795062, 13063795063, 13063795064, 13063795065, 13063795066, 13063795067, 13063795068, 13063795069, 13063762685, 13063762684, 13063762683, 13063762682, 13063762681], "tags": {"highway": "unclassified", "source": "esriWorld"}}, {"type": "way", "id": 1004398874, "nodes": [663331141, 6875510160, 663331143, 663331145, 663331146, 663331147, 663331127, 663331129, 663331130, 663331131, 663331132, 663331133, 663331134, 663331135, 663331136, 663331137, 663331115, 663331116, 663331117, 663331118, 663331119, 663331120, 663331121, 663331122, 663331123, 663331124, 663331125, 663331126, 663331102, 663331104, 663331106, 663331108, 663331109, 663331110, 663331111, 663331112, 663331113, 663331114, 663331090, 663331091, 663331093, 663331094, 13063795226, 663331095, 663331096, 663331097, 663331098, 663331099, 663331101, 663330753, 663330754, 663330755, 663330756, 663330757, 663330758, 663330759, 663330760, 13063762689, 663330761, 663330745, 663330746, 663330747, 663330748, 663330749, 663330750, 663330751, 9267280138, 663330752, 9267280134, 9267280133], "tags": {"highway": "trunk", "int_ref": "G317", "name": "\u6210\u90fd - \u5676\u5c14", "ref": "G317", "source": "GPS"}}, {"type": "way", "id": 1421754907, "nodes": [13065419000, 13065418999], "tags": {"highway": "residential", "source": "esriWorld"}}, {"type": "way", "id": 1421754908, "nodes": [13065386870, 13065386869], "tags": {"highway": "residential", "source": "esriWorld"}}, {"type": "way", "id": 1421754921, "nodes": [13065419034, 13065419032, 13065419031], "tags": {"highway": "residential", "source": "esriWorld"}}, {"type": "way", "id": 1421754937, "nodes": [13065398239, 2034743178, 2034743152, 2034743193], "tags": {"highway": "residential"}}]}